fakturoid/__init__.py
fakturoid/api.py
fakturoid/models.py
fakturoid/paging.py
fakturoid/six.py
fakturoid-1.5.1.dist-info/AUTHORS
fakturoid-1.5.1.dist-info/LICENSE
fakturoid-1.5.1.dist-info/METADATA
fakturoid-1.5.1.dist-info/WHEEL
fakturoid-1.5.1.dist-info/top_level.txt
fakturoid-1.5.1.dist-info/RECORD
