Metadata-Version: 2.1
Name: fakturoid
Version: 1.5.1
Summary: Python API for fakturoid.cz
Home-page: https://github.com/farin/python-fakturoid
Author: Roman Krejcik
Author-email: farin@farin.cz
License: MIT
Keywords: fakturoid,accounting
Platform: any
Classifier: Development Status :: 5 - Production/Stable
Classifier: Intended Audience :: Developers
Classifier: License :: OSI Approved :: MIT License
Classifier: Operating System :: OS Independent
Classifier: Programming Language :: Python :: 2.6
Classifier: Programming Language :: Python :: 2.7
Classifier: Programming Language :: Python :: 3
Classifier: Topic :: Office/Business :: Financial :: Accounting
Requires-Dist: requests
Requires-Dist: python-dateutil
